countdowner/__init__.py
countdowner/cli.py
countdowner/main.py
countdowner-0.3.1.dist-info/DESCRIPTION.rst
countdowner-0.3.1.dist-info/METADATA
countdowner-0.3.1.dist-info/RECORD
countdowner-0.3.1.dist-info/WHEEL
countdowner-0.3.1.dist-info/entry_points.txt
countdowner-0.3.1.dist-info/metadata.json
countdowner-0.3.1.dist-info/top_level.txt
