Metadata-Version: 2.0
Name: countdowner
Version: 0.3.1
Summary: A Python 3.5+ package to check for sales at Countdowngrocery stores throughout New Zealand
Home-page: https://github.com/araichev/countdowner
Author: Alex Raichev
Author-email: UNKNOWN
License: The MIT License
Requires-Dist: PyYAML (>=3.12)
Requires-Dist: beautifulsoup4 (>=4.6.0)
Requires-Dist: click (>=6.7)
Requires-Dist: grequests (>=0.3.0)
Requires-Dist: lxml (>=3.7.3)
Requires-Dist: pandas (>=0.19.0)
Requires-Dist: requests (>=2.14.2)
